__init__.py
user_agent_tools.py
user_agent_tools-0.1.1.dist-info/LICENSE
user_agent_tools-0.1.1.dist-info/METADATA
user_agent_tools-0.1.1.dist-info/WHEEL
user_agent_tools-0.1.1.dist-info/top_level.txt
user_agent_tools-0.1.1.dist-info/RECORD
