Metadata-Version: 2.1
Name: user-agent-tools
Version: 0.1.1
Summary: Simple user agent generator and interpreter tools
Home-page: https://github.com/philiporange/user-agent-tools
Author: Philip Orange
Author-email: git@philiporange.com
License: UNKNOWN
Platform: UNKNOWN
Classifier: Development Status :: 3 - Alpha
Classifier: Intended Audience :: Developers
Classifier: License :: CC0 1.0 Universal (CC0 1.0) Public Domain Dedication
Classifier: Operating System :: OS Independent
Classifier: Programming Language :: Python :: 3
Classifier: Programming Language :: Python :: 3.6
Classifier: Programming Language :: Python :: 3.7
Classifier: Programming Language :: Python :: 3.8
Classifier: Programming Language :: Python :: 3.9
Requires-Python: >=3.6
License-File: LICENSE
Provides-Extra: dev
Requires-Dist: black ; extra == 'dev'
Requires-Dist: pytest (>=3.7) ; extra == 'dev'
